dynamiks/__init__.py
dynamiks/views.py
dynamiks/dwm/__init__.py
dynamiks/dwm/added_turbulence_models.py
dynamiks/dwm/flow_simulation.py
dynamiks/dwm/particle_motion_models.py
dynamiks/dwm/particles_model.py
dynamiks/dwm/particle_deficit_profiles/__init__.py
dynamiks/dwm/particle_deficit_profiles/ainslie.py
dynamiks/dwm/particle_deficit_profiles/particle_deficit_profile.py
dynamiks/dwm/particle_deficit_profiles/pywake_deficit_wrapper.py
dynamiks/dwm/step_handlers/__init__.py
dynamiks/sites/__init__.py
dynamiks/sites/_site.py
dynamiks/sites/turbulence_fields.py
dynamiks/utils/__init__.py
dynamiks/utils/data_dumper.py
dynamiks/utils/geometry.py
dynamiks/utils/test_utils.py
dynamiks/visualizers/__init__.py
dynamiks/visualizers/flow_visualizers.py
dynamiks/visualizers/visualizer_utils.py
dynamiks/wind_turbines/__init__.py
dynamiks/wind_turbines/_windTurbines.py
dynamiks/wind_turbines/axisymetric_induction.py
dynamiks/wind_turbines/hawc2_windturbine.py
dynamiks/wind_turbines/pywake_windturbines.py
dynamiks-0.0.2.dist-info/METADATA
dynamiks-0.0.2.dist-info/WHEEL
dynamiks-0.0.2.dist-info/licenses/LICENSE
dynamiks-0.0.2.dist-info/RECORD
