Metadata-Version: 2.1
Name: dynamiks
Version: 0.0.2
Summary: Dynamic wind system simulator
Project-URL: Homepage, https://gitlab.windenergy.dtu.dk/DYNAMIKS/dynamiks
Project-URL: Bug Tracker, https://gitlab.windenergy.dtu.dk/DYNAMIKS/dynamiks/-/issues
Author-email: "Mads M. Pedersen" <mmpe@dtu.dk>
License-File: LICENSE
Classifier: Operating System :: OS Independent
Classifier: Programming Language :: Python :: 3
Requires-Python: >=3.7
Requires-Dist: hipersim
Requires-Dist: jdwm
Requires-Dist: matplotlib
Requires-Dist: numpy
Requires-Dist: py-wake
Requires-Dist: tqdm
Requires-Dist: xarray
Provides-Extra: test
Requires-Dist: h2lib; extra == 'test'
Requires-Dist: h2lib-tests; extra == 'test'
